LICENSE
MANIFEST.in
README.md
README.rst
package.json
setup.py
filesequence/__init__.py
filesequence/cli.py
filesequence.egg-info/PKG-INFO
filesequence.egg-info/SOURCES.txt
filesequence.egg-info/dependency_links.txt
filesequence.egg-info/entry_points.txt
filesequence.egg-info/top_level.txt