Metadata-Version: 1.0
Name: filesequence
Version: 0.1.11
Summary: Write to an indexed sequence of files using the standard Python file API
Home-page: https://github.com/chbrown/filesequence
Author: Christopher Brown
Author-email: io@henrian.com
License: Copyright (c) 2013 Christopher Brown
